PytorchCNNModules/__init__.py
PytorchCNNModules-0.0.1.dist-info/LICENSE
PytorchCNNModules-0.0.1.dist-info/METADATA
PytorchCNNModules-0.0.1.dist-info/WHEEL
PytorchCNNModules-0.0.1.dist-info/top_level.txt
PytorchCNNModules-0.0.1.dist-info/RECORD
